palworld_pal_edit/EmptyObjectHandler.py
palworld_pal_edit/PalEdit.py
palworld_pal_edit/PalEditLogger.py
palworld_pal_edit/PalInfo.py
palworld_pal_edit/SaveConverter.py
palworld_pal_edit/__init__.py
palworld_pal_edit/resources/MossandaIcon.ico
palworld_pal_edit/resources/MossandaIcon.png
palworld_pal_edit/resources/data/attacks.json
palworld_pal_edit/resources/data/attacks_zh-CN.json
palworld_pal_edit/resources/data/elements.json
palworld_pal_edit/resources/data/pals.json
palworld_pal_edit/resources/data/passives.json
palworld_pal_edit/resources/data/passives_zh-CN.json
palworld_pal_edit/resources/data/ui-lang.json
palworld_pal_edit/resources/data/ui.json
palworld_pal_edit/resources/data/ui_zh-CN.json
palworld_pal_edit/resources/icons/cooling.png
palworld_pal_edit/resources/icons/deforesting.png
palworld_pal_edit/resources/icons/extracting.png
palworld_pal_edit/resources/icons/farming.png
palworld_pal_edit/resources/icons/gathering.png
palworld_pal_edit/resources/icons/generating.png
palworld_pal_edit/resources/icons/handiwork.png
palworld_pal_edit/resources/icons/kindling.png
palworld_pal_edit/resources/icons/mining.png
palworld_pal_edit/resources/icons/no_cooling.png
palworld_pal_edit/resources/icons/no_deforesting.png
palworld_pal_edit/resources/icons/no_extracting.png
palworld_pal_edit/resources/icons/no_farming.png
palworld_pal_edit/resources/icons/no_gathering.png
palworld_pal_edit/resources/icons/no_generating.png
palworld_pal_edit/resources/icons/no_handiwork.png
palworld_pal_edit/resources/icons/no_kindling.png
palworld_pal_edit/resources/icons/no_mining.png
palworld_pal_edit/resources/icons/no_planting.png
palworld_pal_edit/resources/icons/no_production.png
palworld_pal_edit/resources/icons/no_transporting.png
palworld_pal_edit/resources/icons/no_watering.png
palworld_pal_edit/resources/icons/planting.png
palworld_pal_edit/resources/icons/production.png
palworld_pal_edit/resources/icons/transporting.png
palworld_pal_edit/resources/icons/watering.png
palworld_server_toolkit-0.8.5.dist-info/LICENSE
palworld_server_toolkit-0.8.5.dist-info/METADATA
palworld_server_toolkit-0.8.5.dist-info/WHEEL
palworld_server_toolkit-0.8.5.dist-info/entry_points.txt
palworld_server_toolkit-0.8.5.dist-info/top_level.txt
palworld_server_toolkit-0.8.5.dist-info/RECORD
