Metadata-Version: 2.1
Name: palworld-server-toolkit
Version: 0.8.5
Summary: A toolset for PalWorld Server
Home-page: https://github.com/magicbear/palworld-server-toolkit
Author: MagicBear
Author-email: MagicBear <magicbearmo@gmail.com>
License: MIT License
Project-URL: Homepage, https://github.com/magicbear/palworld-server-toolkit
Project-URL: Issues, https://github.com/magicbear/palworld-server-toolkit/issues
Keywords: palworld
Classifier: Programming Language :: Python :: 3
Classifier: License :: OSI Approved :: MIT License
Classifier: Operating System :: OS Independent
Requires-Python: >=3.9
License-File: LICENSE
Requires-Dist: palworld-save-tools >=0.18.0
Requires-Dist: pyperclip
Requires-Dist: recordclass
Requires-Dist: msgpack
Requires-Dist: cityhash
Requires-Dist: palworld-coord
